openapi_perf/__init__.py
openapi_perf/core/__init__.py
openapi_perf/core/_exec.py
openapi_perf/core/_gen.py
openapi_perf/core/_types.py
openapi_perf/core/_utils.py
openapi_perf/core/perf.py
openapi_perf/core/results.py
openapi_perf/core/analysis/__init__.py
openapi_perf/core/analysis/graphing.py
openapi_perf/core/schemas/__init__.py
openapi_perf/core/schemas/test.py
openapi_perf-0.0.5.dist-info/LICENSE
openapi_perf-0.0.5.dist-info/METADATA
openapi_perf-0.0.5.dist-info/WHEEL
openapi_perf-0.0.5.dist-info/top_level.txt
openapi_perf-0.0.5.dist-info/RECORD
